ibapi_grease/__init__.py
ibapi_grease/_version.py
ibapi_grease/lock.py
ibapi_grease/log.py
ibapi_grease-0.2.0.dist-info/DESCRIPTION.rst
ibapi_grease-0.2.0.dist-info/METADATA
ibapi_grease-0.2.0.dist-info/RECORD
ibapi_grease-0.2.0.dist-info/WHEEL
ibapi_grease-0.2.0.dist-info/metadata.json
ibapi_grease-0.2.0.dist-info/top_level.txt
